gitvtag/__init__.py
gitvtag/cli.py
gitvtag/Git.py
gitvtag-0.2.dist-info/DESCRIPTION.rst
gitvtag-0.2.dist-info/entry_points.txt
gitvtag-0.2.dist-info/METADATA
gitvtag-0.2.dist-info/metadata.json
gitvtag-0.2.dist-info/RECORD
gitvtag-0.2.dist-info/top_level.txt
gitvtag-0.2.dist-info/WHEEL
