Metadata-Version: 2.0
Name: gitvtag
Version: 0.2
Summary: A git subcommand for simple and straightforward version tagging
Home-page: https://github.com/SashaOv/git-vtag
Author: Sasha Ovsankin
Author-email: sasha@ovsankin.com
License: Apache License, Version 2.0
Platform: UNKNOWN
